MANIFEST.in
README.txt
setup.py
bin/serapeum-backup
config/example.ini
remotes/list.json
selection/excludes.json
selection/sources.json
serapeum.backup.egg-info/PKG-INFO
serapeum.backup.egg-info/SOURCES.txt
serapeum.backup.egg-info/dependency_links.txt
serapeum.backup.egg-info/top_level.txt
serapeum/backup/__init__.py
serapeum/backup/modules/__init__.py
serapeum/backup/modules/error.py
serapeum/backup/modules/config/__init__.py
serapeum/backup/modules/config/arguments.py
serapeum/backup/modules/ds/__init__.py
serapeum/backup/modules/ds/stack.py
serapeum/backup/modules/files/__init__.py
serapeum/backup/modules/log/__init__.py
serapeum/backup/modules/mail/__init__.py
serapeum/backup/modules/mysql/__init__.py
serapeum/backup/modules/rdiff/__init__.py
serapeum/backup/modules/remotes/__init__.py
serapeum/backup/modules/run/__init__.py