Metadata-Version: 1.0
Name: serapeum.backup
Version: 1.0.7
Summary: Backup script based on rdiff-backup.
Home-page: https://github.com/pieterdp/serapeum.backup
Author: Pieter De Praetere
Author-email: pieter.de.praetere@helptux.be
License: GPLv3
Platform: UNKNOWN
